stelardataprofiler/__init__.py
stelardataprofiler/main.py
stelardataprofiler/profiler.py
stelardataprofiler/utils.py
stelardataprofiler/hierarchical/profiler.py
stelardataprofiler/mappings/hierarchical_mapping.ttl
stelardataprofiler/mappings/raster_mapping.ttl
stelardataprofiler/mappings/rdfgraph_mapping.ttl
stelardataprofiler/mappings/tabular_mapping.ttl
stelardataprofiler/mappings/textual_mapping.ttl
stelardataprofiler/raster/profiler.py
stelardataprofiler/rdfGraph/profiler.py
stelardataprofiler/tabular_timeseries/profiler.py
stelardataprofiler/tabular_timeseries/variables/__init__.py
stelardataprofiler/tabular_timeseries/variables/boolean.py
stelardataprofiler/tabular_timeseries/variables/categorical.py
stelardataprofiler/tabular_timeseries/variables/datetime.py
stelardataprofiler/tabular_timeseries/variables/geometry.py
stelardataprofiler/tabular_timeseries/variables/numeric.py
stelardataprofiler/tabular_timeseries/variables/textual.py
stelardataprofiler/tabular_timeseries/variables/timeseries.py
stelardataprofiler/tabular_timeseries/variables/utils.py
stelardataprofiler/tabular_timeseries/variables/versions.py
stelardataprofiler/text/profiler.py
streamlitapp/__init__.py
streamlitapp/app.py
streamlitapp/profile_functions.py
streamlitapp/.streamlit/config.toml
streamlitapp/icons/stelar_icon.jpg
stelardataprofiler-0.0.4.dist-info/LICENSE
stelardataprofiler-0.0.4.dist-info/METADATA
stelardataprofiler-0.0.4.dist-info/WHEEL
stelardataprofiler-0.0.4.dist-info/entry_points.txt
stelardataprofiler-0.0.4.dist-info/top_level.txt
stelardataprofiler-0.0.4.dist-info/RECORD
