Metadata-Version: 2.1
Name: stelardataprofiler
Version: 0.0.4
Summary: stelardataprofiler is a Python library providing various functions for profiling different types of data and files.
Author-email: Panagiotis Betchavas <pbetchavas@athenarc.gr>
License: Apache License
Project-URL: Homepage, https://github.com/stelar-eu/data-profiler
Classifier: License :: OSI Approved :: Apache Software License
Classifier: Programming Language :: Python
Requires-Python: !=3.9.7,<3.13,>=3.8
License-File: LICENSE
Requires-Dist: jupyter-server ==1.24.0
Requires-Dist: jupyter ==1.0.0
Requires-Dist: DataProfiler ==0.8.9
Requires-Dist: panel ==0.12.4
Requires-Dist: numpy ==1.23.5
Requires-Dist: notebook ==6.4.5
Requires-Dist: Jinja2 ==3.0.1
Requires-Dist: tqdm ==4.64.1
Requires-Dist: Flask ==2.0.3
Requires-Dist: scikit-learn ==1.0.2
Requires-Dist: statsmodels ==0.14.1
Requires-Dist: matplotlib ==3.6.3
Requires-Dist: requests ==2.28.2
Requires-Dist: scipy ==1.9.3
Requires-Dist: pandas ==1.5.3
Requires-Dist: PyYAML ==6.0
Requires-Dist: shapely ==2.0.1
Requires-Dist: tsfresh ==0.20.1
Requires-Dist: rasterio ==1.2.10
Requires-Dist: spacy ==3.7.4
Requires-Dist: nltk ==3.8.1
Requires-Dist: pycountry ==22.3.5
Requires-Dist: simplemma ==0.9.1
Requires-Dist: fasttext-langdetect ==1.0.5
Requires-Dist: streamlit ==1.40.1
Requires-Dist: streamlit-option-menu ==0.3.6
Requires-Dist: protobuf ==3.20.0
Requires-Dist: plotly ==5.15.0
Requires-Dist: altair ==5.0.1
Requires-Dist: streamlit-folium ==0.22.1
Requires-Dist: python-dateutil ==2.8.2
Requires-Dist: IPython ==8.12.2
Requires-Dist: gensim ==4.0.1
Requires-Dist: rdflib ==6.3.2
Requires-Dist: pyproj ==3.4.0
Requires-Dist: geopandas ==0.12.1
Requires-Dist: fiona ==1.9.6
Requires-Dist: folium ==0.14.0
Requires-Dist: spacy-language-detection ==0.2.1
Requires-Dist: python-Levenshtein ==0.20.9
Requires-Dist: numba ==0.58.1
Requires-Dist: llvmlite ==0.41.0
Requires-Dist: typing-extensions ==4.12.2
Requires-Dist: param ==1.13.0
Requires-Dist: cramjam ==2.10.0
